reverse_word_TIB/__init__.py
reverse_word_TIB/__main__.py
reverseword_tib-0.0.3.dist-info/METADATA
reverseword_tib-0.0.3.dist-info/WHEEL
reverseword_tib-0.0.3.dist-info/entry_points.txt
reverseword_tib-0.0.3.dist-info/top_level.txt
reverseword_tib-0.0.3.dist-info/RECORD
